Metadata-Version: 2.1
Name: dfsmpy
Version: 0.0.1
Summary: Deterministic, Finite State Machine.
Home-page: https://github.com/jg75/dfsmpy
License: UNKNOWN
Platform: UNKNOWN
